{
  "lives": [
    {
      "name": "4gTV",
      "url": "http://95.179.139.113:5566/4gtv.m3u"
    },
    {
      "name": "Beesport",
      "url": "http://95.179.139.113:5566/beesport.m3u"
    },
    {
      "name": "TheTV",
      "url": "http://95.179.139.113:5566/thetv.m3u"
    },   
    {
      "name": "IPTV组播",
      "url": "https://raw.githubusercontent.com/redrainl/iptv/main/speedtest/zubo_fofa.txt",
      "epg": "https://epg.112114.xyz/?ch={name}&date={date}",
      "logo": "https://epg.112114.xyz/logo/{name}.png"
    }, 
    {
      "name": "YanG-1989",
      "url": "https://tv.iill.top/m3u/Gather"
    },
    {
      "name": "Stream-link",
      "url": "https://www.stream-link.org/stream-link.m3u"
    },
    {
      "name": "epg台灣",
      "url": "https://freetv.fun/test_channels_taiwan.m3u"
    },  
    {
      "name": "tv543",
      "url": "https://tv543.cc/list.php"
    }, 
    {
      "name": "ubtv",
      "url": "https://files.catbox.moe/g4zbng.json"
    }, 
    {
      "name": "anbox118",
      "url": "https://anbox118.serv00.net/iptv.php"
    }   
  ]
}
